{
    "holochain-nixpkgs": {
        "branch": "develop",
        "description": null,
        "homepage": null,
        "owner": "holochain",
        "repo": "holochain-nixpkgs",
        "rev": "42fc135bf2534e8860e6f8f20c226de643aed028",
        "sha256": "1hdn6p9zha9ljgy72ndcnk9yx30x6r165jm7pslgr797zf7an9yc",
        "type": "tarball",
        "url": "https://github.com/holochain/holochain-nixpkgs/archive/42fc135bf2534e8860e6f8f20c226de643aed028.tar.gz",
        "url_template": "https://github.com/<owner>/<repo>/archive/<rev>.tar.gz"
    },
    "scaffolding": {
        "branch": "main",
        "description": "RAD tools to quickly scaffold a new holochain application",
        "homepage": null,
        "owner": "holochain",
        "repo": "scaffolding",
        "rev": "db3096289691f88f505f1f5e3a61415dd4ab2e24",
        "sha256": "0zq2qbqwv0yji5nwg9qwgbq1lqb4cbcvj46s7dxz9sgacnrmlvgk",
        "type": "tarball",
        "url": "https://github.com/holochain/scaffolding/archive/db3096289691f88f505f1f5e3a61415dd4ab2e24.tar.gz",
        "url_template": "https://github.com/<owner>/<repo>/archive/<rev>.tar.gz"
    }
}
