{
    "holochain-nixpkgs": {
        "branch": "develop",
        "description": null,
        "homepage": null,
        "owner": "holochain",
        "repo": "holochain-nixpkgs",
        "rev": "79639fcf3e2078394cd58d299b1294f4f6e754e8",
        "sha256": "1ivpwvrrizl227g55q7l9dww90q7bn01mxqs7bjlk5lvi4g3ppqb",
        "type": "tarball",
        "url": "https://github.com/holochain/holochain-nixpkgs/archive/79639fcf3e2078394cd58d299b1294f4f6e754e8.tar.gz",
        "url_template": "https://github.com/<owner>/<repo>/archive/<rev>.tar.gz"
    },
    "scaffolding": {
        "branch": "main",
        "description": "RAD tools to quickly scaffold a new holochain application",
        "homepage": null,
        "owner": "holochain",
        "repo": "scaffolding",
        "rev": "3db0f13dcc9b7ad5b5e93c058dffbc7d873c2db6",
        "sha256": "008m36j47kbra7byab06slpp6xcx1b4dmwfj14ivklkxqf04nvwc",
        "type": "tarball",
        "url": "https://github.com/holochain/scaffolding/archive/3db0f13dcc9b7ad5b5e93c058dffbc7d873c2db6.tar.gz",
        "url_template": "https://github.com/<owner>/<repo>/archive/<rev>.tar.gz"
    }
}
